{
  "prefix": "Artnet-cntrl",
  "version": "7.4.3",
  "config": "LEDS2_p5-17_SD_RST12",
  "pioenv": "wt32-eth01",
  "files": {
    "latest_enc": "Artnet-cntrl_LEDS2_p5-17_SD_RST12_latest.enc",
    "versioned_enc": "Artnet-cntrl_LEDS2_p5-17_SD_RST12_v7.4.3.enc"
  },
  "hashes": {
    "sha256_versioned_enc": "d96ca9914a597ba279650ba6b09ba71dcf554fa5a363dbdac551ce6c601437d3",
    "sha256_latest_enc": "d96ca9914a597ba279650ba6b09ba71dcf554fa5a363dbdac551ce6c601437d3"
  },
  "encryption": {
    "cipher": "AES-256-GCM",
    "nonce_b64": "hDXB4sn+qd0VqNzR",
    "nonce_len": 12,
    "tag_len": 16,
    "format": "nonce||ciphertext||tag",
    "plain_size": 1323936
  },
  "built_at": "2026-04-12T22:58:52"
}
